{
  "version": "1.0",
  "defaultProvider": "unpkg",
  "libraries": [
    {
      "library": "bootstrap@5.2.3/dist/css/bootstrap.min.css",
      "destination": "wwwroot/lib/bootstrap/css/",
      "files": [
        "bootstrap.min.css"
      ]
    },
    {
      "library": "bootstrap@5.2.3/dist/css/bootstrap.css",
      "destination": "wwwroot/lib/bootstrap/css/",
      "files": [
        "bootstrap.css"
      ]
    },
    {
      "library": "bootstrap@5.2.3/dist/js/bootstrap.bundle.min.js",
      "destination": "wwwroot/lib/bootstrap/js/",
      "files": [
        "bootstrap.bundle.min.js"
      ]
    },
    {
      "library": "bootstrap@5.2.3/dist/js/bootstrap.bundle.js",
      "destination": "wwwroot/lib/bootstrap/js/",
      "files": [
        "bootstrap.bundle.js"
      ]
    }
  ]
} 